{
  "type": "mysticalagriculture:infusion",
  "input": {
    "tag": "forge:dusts/redstone"
  },
  "ingredients": [
    {
      "item": "refinedstorage:advanced_processor"
    },
    {
      "item": "refinedstorage:quartz_enriched_iron"
    },
    {
      "item": "refinedstorage:advanced_processor"
    },
    {
      "item": "refinedstorage:4096k_fluid_storage_part"
    },
    {
      "item": "refinedstorage:advanced_processor"
	},
    {
      "item": "refinedstorage:4096k_fluid_storage_part"
	},
	{
      "item": "refinedstorage:advanced_processor"
	},
	{
      "item": "refinedstorage:4096k_fluid_storage_part"
    }
  ],
  "result": {
    "item": "extradisks:16384k_fluid_storage_part"
  }
}